yzm_mcp_test/__init__.py
yzm_mcp_test-0.2.1.dist-info/WHEEL
yzm_mcp_test-0.2.1.dist-info/entry_points.txt
yzm_mcp_test-0.2.1.dist-info/METADATA
yzm_mcp_test-0.2.1.dist-info/RECORD
